lipidlibrarian/LipidQuery.py
lipidlibrarian/__init__.py
lipidlibrarian/cli.py
lipidlibrarian/sync_alex123_sql_database.py
lipidlibrarian/api/Alex123API.py
lipidlibrarian/api/LinexAPI.py
lipidlibrarian/api/LionAPI.py
lipidlibrarian/api/LipidAPI.py
lipidlibrarian/api/LipidLibrarianAPI.py
lipidlibrarian/api/LipidMapsAPI.py
lipidlibrarian/api/SwissLipidsAPI.py
lipidlibrarian/api/__init__.py
lipidlibrarian/data/adducts.csv
lipidlibrarian/data/alex123/alex123_db.h5
lipidlibrarian/data/linex/linex_data.pbz2
lipidlibrarian/data/lion/lion_association_table.tsv
lipidlibrarian/data/lion/lion_ontology_graph.obo
lipidlibrarian/data/lipidmaps/goslin_converted_names.tsv
lipidlibrarian/data/swisslipids/goslin_converted_names.tsv
lipidlibrarian/lipid/Adduct.py
lipidlibrarian/lipid/DatabaseIdentifier.py
lipidlibrarian/lipid/Fragment.py
lipidlibrarian/lipid/Level.py
lipidlibrarian/lipid/Lipid.py
lipidlibrarian/lipid/Mass.py
lipidlibrarian/lipid/Nomenclature.py
lipidlibrarian/lipid/Ontology.py
lipidlibrarian/lipid/Reaction.py
lipidlibrarian/lipid/Source.py
lipidlibrarian/lipid/StructureIdentifier.py
lipidlibrarian/lipid/Synonym.py
lipidlibrarian/lipid/__init__.py
lipidlibrarian-0.3.1.dist-info/licenses/LICENSE
lipidlibrarian-0.3.1.dist-info/METADATA
lipidlibrarian-0.3.1.dist-info/WHEEL
lipidlibrarian-0.3.1.dist-info/entry_points.txt
lipidlibrarian-0.3.1.dist-info/top_level.txt
lipidlibrarian-0.3.1.dist-info/RECORD
