Metadata-Version: 2.4
Name: lipidlibrarian
Version: 0.3.1
Summary: A Lipidomics Database Explorer Package
Author: Konstantinos Mechteridis, Konstantin Pelz
Author-email: Felix Niedermaier <felix.niedermaier@tum.de>
License-Expression: AGPL-3.0-or-later
Project-URL: Bug Reports, https://github.com/lipitum/lipidlibrarian/issues
Project-URL: Source, https://github.com/lipitum/lipidlibrarian/
Keywords: lipids,bioinformatics,development
Classifier: Programming Language :: Python :: 3
Classifier: Intended Audience :: Science/Research
Classifier: Natural Language :: English
Classifier: Operating System :: OS Independent
Classifier: Operating System :: POSIX :: Linux
Classifier: Topic :: Database :: Front-Ends
Classifier: Topic :: Scientific/Engineering :: Bio-Informatics
Requires-Python: ~=3.11
License-File: LICENSE
Requires-Dist: requests
Requires-Dist: importlib-metadata
Requires-Dist: numpy
Requires-Dist: pandas
Requires-Dist: tables
Requires-Dist: jsons
Requires-Dist: json2html
Requires-Dist: SQLAlchemy
Requires-Dist: PyMySQL
Requires-Dist: networkx
Requires-Dist: obonet
Requires-Dist: ratelimit
Requires-Dist: rdkit
Requires-Dist: func-timeout
Requires-Dist: sparql-dataframe
Requires-Dist: pygoslin
Requires-Dist: linex2
Provides-Extra: dev
Requires-Dist: pytest; extra == "dev"
Requires-Dist: flake8; extra == "dev"
Requires-Dist: rpy2; extra == "dev"
Provides-Extra: test
Requires-Dist: pytest; extra == "test"
Provides-Extra: lint
Requires-Dist: flake8; extra == "lint"
Dynamic: license-file
